pyEMMP/__init__.py
pyEMMP/_adcp_position.py
pyEMMP/_pd0_fields.py
pyEMMP/adcp.py
pyEMMP/comparison_hd.py
pyEMMP/comparison_hd_mt.py
pyEMMP/comparison_hd_mt_animation.py
pyEMMP/comparison_mt.py
pyEMMP/mapview2D.py
pyEMMP/mapview3D.py
pyEMMP/model.py
pyEMMP/obs.py
pyEMMP/pd0.py
pyEMMP/plotting.py
pyEMMP/sscmodel.py
pyEMMP/utils.py
pyEMMP/utils_crs.py
pyEMMP/utils_dfs2_conversion.py
pyEMMP/utils_dfsu.py
pyEMMP/utils_dfsu2d.py
pyEMMP/utils_shapefile.py
pyEMMP/utils_xml.py
pyEMMP/watersample.py
pyemmp-0.0.17.dist-info/licenses/LICENSE
pyemmp-0.0.17.dist-info/METADATA
pyemmp-0.0.17.dist-info/WHEEL
pyemmp-0.0.17.dist-info/top_level.txt
pyemmp-0.0.17.dist-info/RECORD
