Metadata-Version: 2.4
Name: pyEMMP
Version: 0.0.17
Summary: A Python package developed to support EMMP tasks
Author-email: Abbas Jazaeri <abja@dhigroup.com>, Andy Banks <anba@dhigroup.com>
License: Copyright (c) 2025 DHI Water and Environment Inc
Project-URL: Homepage, https://github.com/abja-dhi/CSEMMPGUI
Project-URL: Issues, https://github.com/abja-dhi/CSEMMPGUI/issues
Classifier: Programming Language :: Python :: 3
Classifier: Operating System :: OS Independent
Requires-Python: >=3.9
License-File: LICENSE
Requires-Dist: numpy
Requires-Dist: mikecore
Requires-Dist: mikeio
Requires-Dist: pyproj
Requires-Dist: cmocean
Requires-Dist: PyQt5
Requires-Dist: plotly
Requires-Dist: geopandas
Requires-Dist: scikit-learn
Requires-Dist: matplotlib
Requires-Dist: tqdm
Requires-Dist: scipy
Requires-Dist: cycler
Dynamic: license-file
